<?xml version="1.0" encoding="UTF-8"?>
<site>
   <description url="http://genesez.de/updatesite">
      The Eclipse Update-Site for the GeneSEZ Generator Framework.
   </description>
   <feature url="features/de.genesez.mirror.feature_1.5.0.jar" id="de.genesez.mirror.feature" version="1.5.0">
      <category name="GeneSEZ"/>
   </feature>
   <feature url="features/de.genesez.mirror.emf_1.5.0.jar" id="de.genesez.mirror.emf" version="1.5.0">
      <category name="Mirror"/>
   </feature>
   <feature url="features/de.genesez.mirror.gef_1.5.0.jar" id="de.genesez.mirror.gef" version="1.5.0">
      <category name="Mirror"/>
   </feature>
   <feature url="features/de.genesez.mirror.openarchitectureware_1.5.0.jar" id="de.genesez.mirror.openarchitectureware" version="1.5.0">
      <category name="Mirror"/>
   </feature>
   <feature url="features/de.genesez.mirror.uml2_1.5.0.jar" id="de.genesez.mirror.uml2" version="1.5.0">
      <category name="Mirror"/>
   </feature>
   <feature url="features/de.genesez.mirror.wst_1.5.0.jar" id="de.genesez.mirror.wst" version="1.5.0">
      <category name="Mirror"/>
   </feature>
   <feature url="features/de.genesez.mirror.xsd_1.5.0.jar" id="de.genesez.mirror.xsd" version="1.5.0">
      <category name="Mirror"/>
   </feature>
   <feature url="features/de.genesez.feature_1.5.1.jar" id="de.genesez.feature" version="1.5.1">
      <category name="GeneSEZ"/>
   </feature>
   <category-def name="GeneSEZ" label="GeneSEZ Framework"/>
   <category-def name="Mirror" label="Projects mirrored by GeneSEZ"/>
</site>
